lineout/__init__.py
lineout/data.py
lineout/status_codes.py
lineout/test.py
lineout/url.py
lineout-0.0.4.dist-info/LICENSE
lineout-0.0.4.dist-info/METADATA
lineout-0.0.4.dist-info/WHEEL
lineout-0.0.4.dist-info/top_level.txt
lineout-0.0.4.dist-info/RECORD
