Metadata-Version: 2.1
Name: lineout
Version: 0.0.4
Summary: an api (i.e. the output) util lib for django projects, especially for DRF (django-rest-framework).
Home-page: https://github.com/claydodo/lineout
Author: claydodo
Author-email: claydodo@foxmail.com
License: UNKNOWN
Project-URL: Bug Tracker, https://github.com/claydodo/lineout/issues
Platform: UNKNOWN
Classifier: Programming Language :: Python :: 3
Classifier: License :: OSI Approved :: The Unlicense (Unlicense)
Classifier: Operating System :: OS Independent
Requires-Python: >=3.0
License-File: LICENSE
